phystool/__init__.py
phystool/__main__.py
phystool/__version__.py
phystool/cli.py
phystool/config.py
phystool/evaluation.py
phystool/helper.py
phystool/latex.py
phystool/pdbfile.py
phystool/physgit.py
phystool/physql/__init__.py
phystool/physql/metadata.py
phystool/physql/models.py
phystool/qt/__init__.py
phystool/qt/filter.py
phystool/qt/git.py
phystool/qt/helper.py
phystool/qt/latex.py
phystool/qt/pdbfile.py
phystool/qt/pdf.py
phystool/qt/process.py
phystool/tags.py
phystool-5.2.1.dist-info/WHEEL
phystool-5.2.1.dist-info/entry_points.txt
phystool-5.2.1.dist-info/METADATA
phystool-5.2.1.dist-info/RECORD
