Metadata-Version: 2.3
Name: phystool
Version: 5.2.1
Summary: Exercise database manager for LaTeX files
Author: Jérôme Dufour
Author-email: Jérôme Dufour <jerome.dufour@eduvaud.ch>
Classifier: Programming Language :: Python :: 3
Classifier: License :: OSI Approved :: GNU General Public License v3 (GPLv3)
Classifier: Operating System :: OS Independent
Classifier: Environment :: X11 Applications :: Qt
Classifier: Topic :: Education
Requires-Dist: gitpython>=3.1.40
Requires-Dist: pyside6>=6.9.2
Requires-Dist: ansi2html>=1.9.2
Requires-Dist: rapidfuzz>=3.14.0
Requires-Dist: requests>=2.32.5
Requires-Dist: sqlalchemy>=2.0.43
Requires-Python: >=3.12
Project-URL: Changelog, https://bitbucket.org/jdufour/phystool/src/master/CHANGELOG.md
Project-URL: Documentation, https://phystool.readthedocs.io/fr/latest/
Project-URL: Repository, https://bitbucket.org/jdufour/phystool/src/master/
